earthquakepy/__init__.py
earthquakepy/ims.py
earthquakepy/multidof.py
earthquakepy/opensees_classes.py
earthquakepy/opensees_helper.py
earthquakepy/responseMdof.py
earthquakepy/responseSdof.py
earthquakepy/singledof.py
earthquakepy/timeseries.py
earthquakepy/tsReaders.py
earthquakepy-0.4.1.dist-info/LICENSE
earthquakepy-0.4.1.dist-info/METADATA
earthquakepy-0.4.1.dist-info/WHEEL
earthquakepy-0.4.1.dist-info/top_level.txt
earthquakepy-0.4.1.dist-info/RECORD
