Metadata-Version: 2.1
Name: earthquakepy
Version: 0.4.1
Summary: python library for earthquake engineers.
Home-page: https://github.com/gauthamrdy/earthquakepy
Author: Gautham Reddy, Digvijay Patankar
Author-email: pgrddy@gmail.com, dbpatankar@gmail.com
License: GNU GPLv3
Platform: UNKNOWN
Classifier: Development Status :: 4 - Beta
Classifier: Intended Audience :: Science/Research
Classifier: License :: OSI Approved :: GNU General Public License v3 (GPLv3)
Classifier: Operating System :: OS Independent
Classifier: Programming Language :: Python :: 3.6
Classifier: Programming Language :: Python :: 3.7
Classifier: Programming Language :: Python :: 3.8
Classifier: Programming Language :: Python :: 3.9
Classifier: Programming Language :: Python :: 3.10
Requires-Python: >=3.6
License-File: LICENSE
Requires-Dist: matplotlib
Requires-Dist: numpy
Requires-Dist: scipy>=1.14.1
